{"nodes": [{"id": "c_users_jay_onedrive_desktop_ssc_new_ssc_src_pages_createquiz_jsx", "label": "CreateQuiz.jsx", "file_type": "code", "source_file": "C:\\Users\\JAY\\OneDrive\\Desktop\\SSC_NEW\\ssc\\src\\pages\\CreateQuiz.jsx", "source_location": "L1"}, {"id": "createquiz_createquiz", "label": "CreateQuiz()", "file_type": "code", "source_file": "C:\\Users\\JAY\\OneDrive\\Desktop\\SSC_NEW\\ssc\\src\\pages\\CreateQuiz.jsx", "source_location": "L13"}], "edges": [{"source": "c_users_jay_onedrive_desktop_ssc_new_ssc_src_pages_createquiz_jsx", "target": "react", "relation": "imports_from", "confidence": "EXTRACTED", "source_file": "C:\\Users\\JAY\\OneDrive\\Desktop\\SSC_NEW\\ssc\\src\\pages\\CreateQuiz.jsx", "source_location": "L1", "weight": 1.0}, {"source": "c_users_jay_onedrive_desktop_ssc_new_ssc_src_pages_createquiz_jsx", "target": "fi", "relation": "imports_from", "confidence": "EXTRACTED", "source_file": "C:\\Users\\JAY\\OneDrive\\Desktop\\SSC_NEW\\ssc\\src\\pages\\CreateQuiz.jsx", "source_location": "L2", "weight": 1.0}, {"source": "c_users_jay_onedrive_desktop_ssc_new_ssc_src_pages_createquiz_jsx", "target": "c_users_jay_onedrive_desktop_ssc_new_ssc_src_styles_createquiz_css", "relation": "imports_from", "confidence": "EXTRACTED", "source_file": "C:\\Users\\JAY\\OneDrive\\Desktop\\SSC_NEW\\ssc\\src\\pages\\CreateQuiz.jsx", "source_location": "L10", "weight": 1.0}, {"source": "c_users_jay_onedrive_desktop_ssc_new_ssc_src_pages_createquiz_jsx", "target": "c_users_jay_onedrive_desktop_ssc_new_ssc_src_context_authcontext_tsx", "relation": "imports_from", "confidence": "EXTRACTED", "source_file": "C:\\Users\\JAY\\OneDrive\\Desktop\\SSC_NEW\\ssc\\src\\pages\\CreateQuiz.jsx", "source_location": "L11", "weight": 1.0}, {"source": "c_users_jay_onedrive_desktop_ssc_new_ssc_src_pages_createquiz_jsx", "target": "createquiz_createquiz", "relation": "contains", "confidence": "EXTRACTED", "source_file": "C:\\Users\\JAY\\OneDrive\\Desktop\\SSC_NEW\\ssc\\src\\pages\\CreateQuiz.jsx", "source_location": "L13", "weight": 1.0}], "raw_calls": [{"caller_nid": "createquiz_createquiz", "callee": "useRef", "source_file": "C:\\Users\\JAY\\OneDrive\\Desktop\\SSC_NEW\\ssc\\src\\pages\\CreateQuiz.jsx", "source_location": "L14"}, {"caller_nid": "createquiz_createquiz", "callee": "useRef", "source_file": "C:\\Users\\JAY\\OneDrive\\Desktop\\SSC_NEW\\ssc\\src\\pages\\CreateQuiz.jsx", "source_location": "L15"}, {"caller_nid": "createquiz_createquiz", "callee": "useState", "source_file": "C:\\Users\\JAY\\OneDrive\\Desktop\\SSC_NEW\\ssc\\src\\pages\\CreateQuiz.jsx", "source_location": "L17"}, {"caller_nid": "createquiz_createquiz", "callee": "useState", "source_file": "C:\\Users\\JAY\\OneDrive\\Desktop\\SSC_NEW\\ssc\\src\\pages\\CreateQuiz.jsx", "source_location": "L19"}, {"caller_nid": "createquiz_createquiz", "callee": "useState", "source_file": "C:\\Users\\JAY\\OneDrive\\Desktop\\SSC_NEW\\ssc\\src\\pages\\CreateQuiz.jsx", "source_location": "L29"}, {"caller_nid": "createquiz_createquiz", "callee": "useEffect", "source_file": "C:\\Users\\JAY\\OneDrive\\Desktop\\SSC_NEW\\ssc\\src\\pages\\CreateQuiz.jsx", "source_location": "L35"}, {"caller_nid": "createquiz_createquiz", "callee": "useEffect", "source_file": "C:\\Users\\JAY\\OneDrive\\Desktop\\SSC_NEW\\ssc\\src\\pages\\CreateQuiz.jsx", "source_location": "L60"}, {"caller_nid": "createquiz_createquiz", "callee": "useState", "source_file": "C:\\Users\\JAY\\OneDrive\\Desktop\\SSC_NEW\\ssc\\src\\pages\\CreateQuiz.jsx", "source_location": "L84"}, {"caller_nid": "createquiz_createquiz", "callee": "useState", "source_file": "C:\\Users\\JAY\\OneDrive\\Desktop\\SSC_NEW\\ssc\\src\\pages\\CreateQuiz.jsx", "source_location": "L85"}, {"caller_nid": "createquiz_createquiz", "callee": "useState", "source_file": "C:\\Users\\JAY\\OneDrive\\Desktop\\SSC_NEW\\ssc\\src\\pages\\CreateQuiz.jsx", "source_location": "L86"}, {"caller_nid": "createquiz_createquiz", "callee": "useState", "source_file": "C:\\Users\\JAY\\OneDrive\\Desktop\\SSC_NEW\\ssc\\src\\pages\\CreateQuiz.jsx", "source_location": "L88"}, {"caller_nid": "createquiz_createquiz", "callee": "useState", "source_file": "C:\\Users\\JAY\\OneDrive\\Desktop\\SSC_NEW\\ssc\\src\\pages\\CreateQuiz.jsx", "source_location": "L89"}, {"caller_nid": "createquiz_createquiz", "callee": "useState", "source_file": "C:\\Users\\JAY\\OneDrive\\Desktop\\SSC_NEW\\ssc\\src\\pages\\CreateQuiz.jsx", "source_location": "L91"}, {"caller_nid": "createquiz_createquiz", "callee": "useEffect", "source_file": "C:\\Users\\JAY\\OneDrive\\Desktop\\SSC_NEW\\ssc\\src\\pages\\CreateQuiz.jsx", "source_location": "L92"}, {"caller_nid": "createquiz_createquiz", "callee": "useEffect", "source_file": "C:\\Users\\JAY\\OneDrive\\Desktop\\SSC_NEW\\ssc\\src\\pages\\CreateQuiz.jsx", "source_location": "L101"}, {"caller_nid": "createquiz_createquiz", "callee": "useEffect", "source_file": "C:\\Users\\JAY\\OneDrive\\Desktop\\SSC_NEW\\ssc\\src\\pages\\CreateQuiz.jsx", "source_location": "L107"}, {"caller_nid": "createquiz_createquiz", "callee": "useRef", "source_file": "C:\\Users\\JAY\\OneDrive\\Desktop\\SSC_NEW\\ssc\\src\\pages\\CreateQuiz.jsx", "source_location": "L115"}, {"caller_nid": "createquiz_createquiz", "callee": "useEffect", "source_file": "C:\\Users\\JAY\\OneDrive\\Desktop\\SSC_NEW\\ssc\\src\\pages\\CreateQuiz.jsx", "source_location": "L117"}, {"caller_nid": "createquiz_createquiz", "callee": "map", "source_file": "C:\\Users\\JAY\\OneDrive\\Desktop\\SSC_NEW\\ssc\\src\\pages\\CreateQuiz.jsx", "source_location": "L529"}]}